oneseismic/__init__.py
oneseismic/__main__.py
oneseismic/decoding/__init__.py
oneseismic/decoding/decoder.cp310-win32.pyd
oneseismic/decoding/decoding.py
oneseismic/decoding/xarray.py
oneseismic/internal/__init__.py
oneseismic/internal/argparse.py
oneseismic/internal/blobfs.py
oneseismic/internal/localfs.py
oneseismic/internal/process.py
oneseismic/internal/test_argparse.py
oneseismic/internal/test_process.py
oneseismic/scan/__init__.py
oneseismic/scan/__main__.py
oneseismic/scan/scan.py
oneseismic/scan/scanners.py
oneseismic/simple/__init__.py
oneseismic/simple/aztools.py
oneseismic/simple/simple_client.py
oneseismic/simple/test_simple.py
oneseismic/upload/__init__.py
oneseismic/upload/__main__.py
oneseismic/upload/upload.py
oneseismic-0.4.0.dist-info/LICENSE
oneseismic-0.4.0.dist-info/METADATA
oneseismic-0.4.0.dist-info/WHEEL
oneseismic-0.4.0.dist-info/top_level.txt
oneseismic-0.4.0.dist-info/RECORD
