Metadata-Version: 2.1
Name: oneseismic
Version: 0.4.0
Summary: oneseismic
Home-page: https://github.com/equinor/oneseismic
License: LGPL-3.0
Platform: UNKNOWN
License-File: LICENSE
Requires-Dist: azure-storage-blob
Requires-Dist: azure-identity
Requires-Dist: gql
Requires-Dist: numpy
Requires-Dist: requests
Requires-Dist: segyio
Requires-Dist: tqdm
Requires-Dist: xarray
Requires-Dist: importlib-metadata (>='1.0') ; python_version < "3.8"
